palindrome_validator_checker/__init__.py
palindrome_validator_checker/checker.py
palindrome_validator_checker-0.1.dist-info/METADATA
palindrome_validator_checker-0.1.dist-info/WHEEL
palindrome_validator_checker-0.1.dist-info/top_level.txt
palindrome_validator_checker-0.1.dist-info/RECORD
