Metadata-Version: 2.1
Name: palindrome-validator-checker
Version: 0.1
Summary: A Python library to validate if a string is a palindrome.
Author: Your Name
Requires-Python: >=3.6
